locaya/__init__.py
locaya/language.py
locaya/loader/__init__.py
locaya/loader/base.py
locaya/loader/yaml.py
locaya/localization.py
locaya/locaya.py
locaya-0.0.1a1.dist-info/METADATA
locaya-0.0.1a1.dist-info/WHEEL
locaya-0.0.1a1.dist-info/RECORD
