Metadata-Version: 2.1
Name: locaya
Version: 0.0.1a1
Summary: Simple YAML-based localization system
Author: Respirens
Author-email: thesergiyprotsanin@gmail.com
Requires-Python: >=3.10,<4.0
Classifier: Programming Language :: Python :: 3
Classifier: Programming Language :: Python :: 3.10
Classifier: Programming Language :: Python :: 3.11
Requires-Dist: pyyaml (>=6.0,<7.0)
